app_monitoring/__init__.py
app_monitoring/cli.py
app_monitoring/monitor.py
app_monitoring/package_version.txt
app_monitoring-1.2.1.dist-info/LICENSE
app_monitoring-1.2.1.dist-info/METADATA
app_monitoring-1.2.1.dist-info/WHEEL
app_monitoring-1.2.1.dist-info/entry_points.txt
app_monitoring-1.2.1.dist-info/top_level.txt
app_monitoring-1.2.1.dist-info/RECORD
