Metadata-Version: 2.1
Name: app_monitoring
Version: 1.2.1
Summary: A to monitoring my app.
Home-page: http://gitea:8000/datlt4/fortifai_monitoring
Author: Koi
Author-email: your.email@example.com
Classifier: Programming Language :: Python :: 3
Classifier: License :: OSI Approved :: MIT License
Classifier: Operating System :: OS Independent
Requires-Python: >=3.6
License-File: LICENSE
